.gitignore
.project
CHANGES.txt
COPYRIGHT.txt
LICENSE.txt
README.txt
buildout.cfg
setup.cfg
setup.py
src/randenc/__init__.py
src/randenc/enc.py
src/randenc/keys.py
src/randenc.egg-info/PKG-INFO
src/randenc.egg-info/SOURCES.txt
src/randenc.egg-info/dependency_links.txt
src/randenc.egg-info/entry_points.txt
src/randenc.egg-info/not-zip-safe
src/randenc.egg-info/requires.txt
src/randenc.egg-info/top_level.txt
src/randenc/tests/__init__.py
src/randenc/tests/test_keys.py
src/randenc/tests/test_randenc.py