Metadata-Version: 1.0
Name: randenc
Version: 0.1
Summary: Randomized Encryption Library
Home-page: https://github.com/hathawsh/randenc
Author: Shane Hathaway
Author-email: shane@hathawaymix.org
License: BSD-derived (http://www.repoze.org/LICENSE.txt)
Keywords: encrypt
Platform: UNKNOWN
Classifier: Development Status :: 3 - Alpha
Classifier: Intended Audience :: Developers
Classifier: Programming Language :: Python
